<?xml version="1.0" encoding="ISO-8859-1"?>
<!-- generated by ThinG, the Thinlet GUI editor -->
<panel border="true" bottom="6" columns="2" gap="6" left="6" name="fieldspanel" right="6" top="6" valign="top" weightx="1" weighty="1">
    <label colspan="2" name="infolabel" text="Info:"/>
    <textfield columns="1" end="4" name="namefield" start="4" text="name" weightx="1"/>
    <label name="namerequired" text="*"/>
    <combobox end="6" name="genderfield" start="6" text="gender" weightx="1">
        <choice name="malechoice" text="Male"/>
        <choice name="femalechoice" text="Female"/>
        <choice name="transgenderchoice" text="Transgender"/>
    </combobox>
    <label name="genderrequired" text="*"/>
    <textfield end="9" name="birthdatefield" start="9" text="birthdate" weightx="1"/>
    <label name="birthdaterequired" text="*"/>
</panel>
